<?xml version="1.0" encoding='UTF-8'?>
<!DOCTYPE hibernate-mapping PUBLIC
        "-//Hibernate/Hibernate Mapping DTD 3.0//EN"
        "http://hibernate.sourceforge.net/hibernate-mapping-3.0.dtd" >
<hibernate-mapping package="com.scutcms.DAO.entity">
    <class name="Salary" table="SALARY">
        <id name="employeeID" column="EMPLOYEE_ID"></id>
        <property name="salary_DATE" column="SALARY_DATE"></property>
        <property name="salary" column="SALARY"></property>
    </class>
</hibernate-mapping>